odoo8_addon_l10n_account_translate-8.0.0.2.0-py2.7-nspkg.pth
odoo_addons/l10n_account_translate/__openerp__.py
odoo_addons/l10n_account_translate/__init__.py
odoo_addons/l10n_account_translate/README.rst
odoo_addons/l10n_account_translate/models/account.py
odoo_addons/l10n_account_translate/models/__init__.py
odoo8_addon_l10n_account_translate-8.0.0.2.0.dist-info/top_level.txt
odoo8_addon_l10n_account_translate-8.0.0.2.0.dist-info/WHEEL
odoo8_addon_l10n_account_translate-8.0.0.2.0.dist-info/RECORD
odoo8_addon_l10n_account_translate-8.0.0.2.0.dist-info/metadata.json
odoo8_addon_l10n_account_translate-8.0.0.2.0.dist-info/DESCRIPTION.rst
odoo8_addon_l10n_account_translate-8.0.0.2.0.dist-info/METADATA
odoo8_addon_l10n_account_translate-8.0.0.2.0.dist-info/namespace_packages.txt
